nanokv/__init__.py
nanokv/decoder.py
nanokv/encoder.py
nanokv-0.1.0.dist-info/WHEEL
nanokv-0.1.0.dist-info/METADATA
nanokv-0.1.0.dist-info/RECORD
