Metadata-Version: 2.3
Name: nanokv
Version: 0.1.0
Summary: A minimal key-value serialization format
Author: Tom Clesius
Author-email: Tom Clesius <tomclesius@gmail.com>
Requires-Python: >=3.13
